Arrays/__init__.py
Arrays/arrays.py
Arrays-0.0.5.dist-info/METADATA
Arrays-0.0.5.dist-info/RECORD
Arrays-0.0.5.dist-info/WHEEL
Arrays-0.0.5.dist-info/top_level.txt
