Metadata-Version: 2.1
Name: Arrays
Version: 0.0.5
Summary: Python library for storing and reading stored arrays.
Home-page: https://github.com/S0FTY/Arrays
Author: RedDog
Author-email: bremo.lincolin101@gmail.com
License: UNKNOWN
Platform: UNKNOWN
Classifier: Programming Language :: Python :: 3
Classifier: License :: OSI Approved :: MIT License
Classifier: Operating System :: OS Independent
